gitstats/__init__.py
gitstats/arrow-down.gif
gitstats/arrow-none.gif
gitstats/arrow-up.gif
gitstats/gitstats.css
gitstats/main.py
gitstats/report_creator.py
gitstats/sortable.js
gitstats/utils.py
gitstats-1.5.0.dist-info/licenses/LICENSE
gitstats-1.5.0.dist-info/METADATA
gitstats-1.5.0.dist-info/WHEEL
gitstats-1.5.0.dist-info/entry_points.txt
gitstats-1.5.0.dist-info/top_level.txt
gitstats-1.5.0.dist-info/RECORD
