Metadata-Version: 2.4
Name: gitstats
Version: 1.5.0
Summary: GitStats - Visualize Your Git Repositories
Author-email: Xianpeng Shen <xianpeng.shen@gmail.com>, Heikki Hokkanen <hoxu@users.sf.net>
Project-URL: source, https://github.com/shenxianpeng/gitstats
Project-URL: tracker, https://github.com/shenxianpeng/gitstats/issues
Project-URL: homepage, https://shenxianpeng.github.io/gitstats/index.html
Project-URL: documentation, https://gitstats.readthedocs.io/
Keywords: git,gitstats,statistics,git history
Classifier: Development Status :: 5 - Production/Stable
Classifier: Intended Audience :: Developers
Classifier: Natural Language :: English
Classifier: Programming Language :: Python :: 3.9
Classifier: Programming Language :: Python :: 3.10
Classifier: Programming Language :: Python :: 3.11
Classifier: Programming Language :: Python :: 3.12
Classifier: Programming Language :: Python :: 3.13
Classifier: Programming Language :: Python :: 3.14
Classifier: Topic :: Software Development :: Build Tools
Classifier: Operating System :: Microsoft :: Windows
Classifier: Operating System :: POSIX :: Linux
Classifier: Operating System :: MacOS
Requires-Python: >=3.9
License-File: LICENSE
Requires-Dist: gnuplot-wheel
Provides-Extra: dev
Requires-Dist: nox; extra == "dev"
Provides-Extra: docs
Requires-Dist: sphinx; extra == "docs"
Requires-Dist: sphinx-rtd-theme; extra == "docs"
Requires-Dist: sphinx-autobuild; extra == "docs"
Dynamic: license-file
